{
  "type": "FeatureCollection",
  "features": [
    {
      "type": "Feature",
      "properties": {},
      "geometry": {
        "type": "LineString",
        "coordinates": [
          [
            23.30897569656372,
            42.69431998301352
          ],
          [
            23.309190273284912,
            42.693862622360555
          ],
          [
            23.309630155563354,
            42.69338948710613
          ],
          [
            23.310059309005737,
            42.69267977746608
          ],
          [
            23.311303853988644,
            42.69150479590089
          ],
          [
            23.31275224685669,
            42.69046385406597
          ],
          [
            23.314114809036255,
            42.68933614739119
          ],
          [
            23.31452250480652,
            42.68877622947772
          ],
          [
            23.31449031829834,
            42.6882951692112
          ],
          [
            23.313653469085693,
            42.6877510145831
          ],
          [
            23.314661979675293,
            42.686922944046245
          ],
          [
            23.31371784210205,
            42.68637089088913
          ],
          [
            23.313342332839966,
            42.685834605981576
          ],
          [
            23.31226944923401,
            42.68554280195462
          ],
          [
            23.31101417541504,
            42.68657593977733
          ],
          [
            23.31053137779236,
            42.68671789630345
          ],
          [
            23.30966234207153,
            42.68756962864777
          ],
          [
            23.308589458465573,
            42.68838980431209
          ],
          [
            23.308331966400146,
            42.688957611889705
          ],
          [
            23.307151794433594,
            42.689556958701765
          ]
        ]
      }
    },
    {
      "type": "Feature",
      "properties": {},
      "geometry": {
        "type": "LineString",
        "coordinates": [
          [
            23.31519842147827,
            42.695100642553726
          ],
          [
            23.314855098724365,
            42.69480099661794
          ],
          [
            23.315327167510983,
            42.69429632651064
          ],
          [
            23.314855098724365,
            42.69388627902865
          ],
          [
            23.31524133682251,
            42.69338160148803
          ],
          [
            23.31472635269165,
            42.69323966019079
          ],
          [
            23.314404487609863,
            42.69229337658561
          ],
          [
            23.314661979675293,
            42.69185177263572
          ],
          [
            23.314404487609863,
            42.69158365441993
          ],
          [
            23.31425428390503,
            42.69133130680657
          ],
          [
            23.314146995544434,
            42.69070043328764
          ],
          [
            23.31421136856079,
            42.69030613408425
          ]
        ]
      }
    },
    {
      "type": "Feature",
      "properties": {},
      "geometry": {
        "type": "LineString",
        "coordinates": [
          [
            23.307666778564453,
            42.69118936082351
          ],
          [
            23.307666778564453,
            42.69144170901359
          ],
          [
            23.307323455810547,
            42.691536339320514
          ],
          [
            23.307323455810547,
            42.69169405617836
          ],
          [
            23.30719470977783,
            42.69193063071421
          ],
          [
            23.30698013305664,
            42.692025260276225
          ],
          [
            23.30698013305664,
            42.69232491960474
          ],
          [
            23.306593894958496,
            42.69232491960474
          ],
          [
            23.306550979614258,
            42.69268766317329
          ],
          [
            23.306207656860348,
            42.69281383435271
          ]
        ]
      }
    }
  ]
}